{
"meta":{"test_sets":[],"test_metrics":[],"learn_metrics":[{"best_value":"Min","name":"RMSE"}],"launch_mode":"Train","parameters":"","iteration_count":100,"learn_sets":["learn"],"name":"experiment"},
"iterations":[
{"learn":[14.005006],"iteration":0,"passed_time":0.0006867175342,"remaining_time":0.06798503588},
{"learn":[13.14441192],"iteration":1,"passed_time":0.001239015604,"remaining_time":0.06071176459},
{"learn":[12.34258257],"iteration":2,"passed_time":0.001789676953,"remaining_time":0.05786622148},
{"learn":[11.64527793],"iteration":3,"passed_time":0.002179694843,"remaining_time":0.05231267623},
{"learn":[11.02766183],"iteration":4,"passed_time":0.002683785635,"remaining_time":0.05099192706},
{"learn":[10.43485794],"iteration":5,"passed_time":0.003251355131,"remaining_time":0.05093789705},
{"learn":[9.890641275],"iteration":6,"passed_time":0.003734774621,"remaining_time":0.04961914854},
{"learn":[9.492161212],"iteration":7,"passed_time":0.004206037229,"remaining_time":0.04836942814},
{"learn":[9.105082953],"iteration":8,"passed_time":0.004694585689,"remaining_time":0.04746747752},
{"learn":[8.674157135],"iteration":9,"passed_time":0.00519385749,"remaining_time":0.04674471741},
{"learn":[8.341743544],"iteration":10,"passed_time":0.005705007887,"remaining_time":0.04615870018},
{"learn":[8.049372916],"iteration":11,"passed_time":0.006203052798,"remaining_time":0.04548905386},
{"learn":[7.757318612],"iteration":12,"passed_time":0.006673023396,"remaining_time":0.0446579258},
{"learn":[7.522206899],"iteration":13,"passed_time":0.007168570247,"remaining_time":0.04403550294},
{"learn":[7.297756655],"iteration":14,"passed_time":0.007673240186,"remaining_time":0.04348169439},
{"learn":[7.088359431],"iteration":15,"passed_time":0.008133386119,"remaining_time":0.04270027713},
{"learn":[6.882113791],"iteration":16,"passed_time":0.00860349217,"remaining_time":0.0420052853},
{"learn":[6.704728832],"iteration":17,"passed_time":0.009078297388,"remaining_time":0.0413566881},
{"learn":[6.563881962],"iteration":18,"passed_time":0.009551471095,"remaining_time":0.0407194294},
{"learn":[6.418790279],"iteration":19,"passed_time":0.01003503559,"remaining_time":0.04014014236},
{"learn":[6.315756953],"iteration":20,"passed_time":0.01050550198,"remaining_time":0.03952069792},
{"learn":[6.210157751],"iteration":21,"passed_time":0.01098762251,"remaining_time":0.03895611618},
{"learn":[6.115058449],"iteration":22,"passed_time":0.01146855262,"remaining_time":0.03839471966},
{"learn":[6.014819884],"iteration":23,"passed_time":0.01194863876,"remaining_time":0.03783735608},
{"learn":[5.93117229],"iteration":24,"passed_time":0.01244248551,"remaining_time":0.03732745652},
{"learn":[5.844857622],"iteration":25,"passed_time":0.01291855061,"remaining_time":0.0367681825},
{"learn":[5.771145213],"iteration":26,"passed_time":0.01339368143,"remaining_time":0.0362125461},
{"learn":[5.704018229],"iteration":27,"passed_time":0.01389013999,"remaining_time":0.03571750282},
{"learn":[5.665806474],"iteration":28,"passed_time":0.01437072018,"remaining_time":0.03518348734},
{"learn":[5.616500369],"iteration":29,"passed_time":0.01488966302,"remaining_time":0.03474254704},
{"learn":[5.558023666],"iteration":30,"passed_time":0.01537468797,"remaining_time":0.03422107967},
{"learn":[5.510080976],"iteration":31,"passed_time":0.01587386078,"remaining_time":0.03373195417},
{"learn":[5.468747792],"iteration":32,"passed_time":0.01636955872,"remaining_time":0.03323516467},
{"learn":[5.429275534],"iteration":33,"passed_time":0.01684690628,"remaining_time":0.03270281807},
{"learn":[5.402117324],"iteration":34,"passed_time":0.01734773318,"remaining_time":0.03221721876},
{"learn":[5.367635151],"iteration":35,"passed_time":0.01797943954,"remaining_time":0.03196344807},
{"learn":[5.345181232],"iteration":36,"passed_time":0.01858271386,"remaining_time":0.03164083711},
{"learn":[5.319151269],"iteration":37,"passed_time":0.01920557585,"remaining_time":0.03133541323},
{"learn":[5.296134146],"iteration":38,"passed_time":0.01981274052,"remaining_time":0.03098915825},
{"learn":[5.269629003],"iteration":39,"passed_time":0.02050113211,"remaining_time":0.03075169817},
{"learn":[5.251147059],"iteration":40,"passed_time":0.02104530562,"remaining_time":0.03028470809},
{"learn":[5.248003302],"iteration":41,"passed_time":0.02129759978,"remaining_time":0.02941097113},
{"learn":[5.232376509],"iteration":42,"passed_time":0.02186017142,"remaining_time":0.02897743654},
{"learn":[5.213524255],"iteration":43,"passed_time":0.02250835483,"remaining_time":0.02864699705},
{"learn":[5.189691584],"iteration":44,"passed_time":0.02306716201,"remaining_time":0.02819319801},
{"learn":[5.166052198],"iteration":45,"passed_time":0.02376772567,"remaining_time":0.02790124318},
{"learn":[5.140406659],"iteration":46,"passed_time":0.0243790972,"remaining_time":0.02749132237},
{"learn":[5.118929684],"iteration":47,"passed_time":0.02505271359,"remaining_time":0.02714043972},
{"learn":[5.108792602],"iteration":48,"passed_time":0.0256488419,"remaining_time":0.02669573341},
{"learn":[5.098141225],"iteration":49,"passed_time":0.02626246619,"remaining_time":0.02626246619},
{"learn":[5.085926393],"iteration":50,"passed_time":0.02689577107,"remaining_time":0.02584103495},
{"learn":[5.067816804],"iteration":51,"passed_time":0.02747040625,"remaining_time":0.02535729808},
{"learn":[5.049834901],"iteration":52,"passed_time":0.02807026993,"remaining_time":0.02489250352},
{"learn":[5.03838627],"iteration":53,"passed_time":0.02865221782,"remaining_time":0.02440744481},
{"learn":[5.033534248],"iteration":54,"passed_time":0.02899316536,"remaining_time":0.02372168075},
{"learn":[5.023726885],"iteration":55,"passed_time":0.02961398948,"remaining_time":0.02326813459},
{"learn":[5.01290392],"iteration":56,"passed_time":0.03016484272,"remaining_time":0.02275593398},
{"learn":[5.005569127],"iteration":57,"passed_time":0.03071315275,"remaining_time":0.02224055889},
{"learn":[4.989969032],"iteration":58,"passed_time":0.03140872768,"remaining_time":0.02182640398},
{"learn":[4.976762446],"iteration":59,"passed_time":0.03200980045,"remaining_time":0.02133986697},
{"learn":[4.967222715],"iteration":60,"passed_time":0.03267447088,"remaining_time":0.02089023548},
{"learn":[4.954407599],"iteration":61,"passed_time":0.03327440533,"remaining_time":0.02039399036},
{"learn":[4.942125056],"iteration":62,"passed_time":0.03382606521,"remaining_time":0.01986610179},
{"learn":[4.930230716],"iteration":63,"passed_time":0.03441413018,"remaining_time":0.01935794823},
{"learn":[4.921695642],"iteration":64,"passed_time":0.03499878756,"remaining_time":0.01884550099},
{"learn":[4.906405625],"iteration":65,"passed_time":0.03556477938,"remaining_time":0.01832124998},
{"learn":[4.894330248],"iteration":66,"passed_time":0.03617276371,"remaining_time":0.01781643586},
{"learn":[4.88211557],"iteration":67,"passed_time":0.03672653092,"remaining_time":0.01728307338},
{"learn":[4.877946398],"iteration":68,"passed_time":0.03726328406,"remaining_time":0.01674147545},
{"learn":[4.863182126],"iteration":69,"passed_time":0.03778626008,"remaining_time":0.01619411146},
{"learn":[4.84646533],"iteration":70,"passed_time":0.03840269285,"remaining_time":0.01568560694},
{"learn":[4.838014752],"iteration":71,"passed_time":0.03903875888,"remaining_time":0.01518173956},
{"learn":[4.82981137],"iteration":72,"passed_time":0.03963331212,"remaining_time":0.01465889626},
{"learn":[4.817094767],"iteration":73,"passed_time":0.04025753949,"remaining_time":0.0141445409},
{"learn":[4.808314151],"iteration":74,"passed_time":0.04079758517,"remaining_time":0.01359919506},
{"learn":[4.796235023],"iteration":75,"passed_time":0.04133614781,"remaining_time":0.01305352036},
{"learn":[4.784434534],"iteration":76,"passed_time":0.04192783397,"remaining_time":0.01252389846},
{"learn":[4.774402487],"iteration":77,"passed_time":0.0424677125,"remaining_time":0.01197807276},
{"learn":[4.76731896],"iteration":78,"passed_time":0.0430115374,"remaining_time":0.01143344665},
{"learn":[4.75934113],"iteration":79,"passed_time":0.04360799045,"remaining_time":0.01090199761},
{"learn":[4.754106378],"iteration":80,"passed_time":0.04414025888,"remaining_time":0.01035388789},
{"learn":[4.744002932],"iteration":81,"passed_time":0.04473260711,"remaining_time":0.00981935278},
{"learn":[4.731700554],"iteration":82,"passed_time":0.04538627765,"remaining_time":0.009295984579},
{"learn":[4.723284153],"iteration":83,"passed_time":0.04591261048,"remaining_time":0.008745259138},
{"learn":[4.712232782],"iteration":84,"passed_time":0.04642676297,"remaining_time":0.008192958172},
{"learn":[4.703046867],"iteration":85,"passed_time":0.04713839903,"remaining_time":0.007673692866},
{"learn":[4.698601855],"iteration":86,"passed_time":0.04777672174,"remaining_time":0.007139050375},
{"learn":[4.692429407],"iteration":87,"passed_time":0.04845139006,"remaining_time":0.006607007736},
{"learn":[4.675027364],"iteration":88,"passed_time":0.04908153047,"remaining_time":0.006066256575},
{"learn":[4.662368584],"iteration":89,"passed_time":0.04971014182,"remaining_time":0.005523349091},
{"learn":[4.646206172],"iteration":90,"passed_time":0.05022476667,"remaining_time":0.004967284615},
{"learn":[4.641245848],"iteration":91,"passed_time":0.05077537418,"remaining_time":0.004415249929},
{"learn":[4.633900435],"iteration":92,"passed_time":0.05137529561,"remaining_time":0.003866957734},
{"learn":[4.624738236],"iteration":93,"passed_time":0.05192173187,"remaining_time":0.003314153098},
{"learn":[4.612798287],"iteration":94,"passed_time":0.05251729667,"remaining_time":0.002764068246},
{"learn":[4.605222001],"iteration":95,"passed_time":0.05302834417,"remaining_time":0.002209514341},
{"learn":[4.601725912],"iteration":96,"passed_time":0.05367629271,"remaining_time":0.001660091527},
{"learn":[4.59722371],"iteration":97,"passed_time":0.05424652567,"remaining_time":0.001107071953},
{"learn":[4.580235665],"iteration":98,"passed_time":0.05491657862,"remaining_time":0.0005547129153},
{"learn":[4.57591791],"iteration":99,"passed_time":0.05544167847,"remaining_time":0}
]}